mcpdoc/__init__.py
mcpdoc/_version.py
mcpdoc/cli.py
mcpdoc/langgraph.py
mcpdoc/main.py
mcpdoc/splash.py
mcpdoc_fastmcp-0.0.11.dist-info/METADATA
mcpdoc_fastmcp-0.0.11.dist-info/WHEEL
mcpdoc_fastmcp-0.0.11.dist-info/entry_points.txt
mcpdoc_fastmcp-0.0.11.dist-info/licenses/LICENSE
mcpdoc_fastmcp-0.0.11.dist-info/RECORD
