Metadata-Version: 2.4
Name: mcpdoc-fastmcp
Version: 0.0.11
Summary: Server llms-txt documentation over MCP
Project-URL: Homepage, https://github.com/fastmcp-me/mcpdoc#readme
Project-URL: Repository, https://github.com/fastmcp-me/mcpdoc.git
Project-URL: Issues, https://github.com/fastmcp-me/mcpdoc/issues
License-Expression: MIT
License-File: LICENSE
Requires-Python: >=3.10
Requires-Dist: httpx>=0.28.1
Requires-Dist: markdownify>=1.1.0
Requires-Dist: mcp[cli]>=1.4.1
Requires-Dist: pyyaml>=6.0.1
